truncated_gamma/__init__.py
truncated_gamma_rvs/__init__.py
truncated_gamma_rvs/truncated_gamma_rvs.py
truncated_gamma_rvs-0.1.4.dist-info/licenses/LICENSE
truncated_gamma_rvs-0.1.4.dist-info/METADATA
truncated_gamma_rvs-0.1.4.dist-info/WHEEL
truncated_gamma_rvs-0.1.4.dist-info/top_level.txt
truncated_gamma_rvs-0.1.4.dist-info/RECORD
