Metadata-Version: 2.4
Name: truncated-gamma-rvs
Version: 0.1.4
Summary: A Python package for generating random variates from a truncated gamma distribution.
Author-email: "Wade K. Copeland" <wade@kingcopeland.com>
License-Expression: MIT
Project-URL: Homepage, https://www.kingcopeland.com/truncated-gamma-rvs-py/
Project-URL: Repository, https://github.com/wkingc/truncated-gamma-rvs-py-package
Project-URL: Issues, https://github.com/wkingc/truncated-gamma-rvs-py-package/issues
Classifier: Development Status :: 3 - Alpha
Classifier: Intended Audience :: Developers
Classifier: Intended Audience :: Science/Research
Classifier: Operating System :: OS Independent
Classifier: Programming Language :: Python :: 3
Classifier: Programming Language :: Python :: 3.9
Classifier: Programming Language :: Python :: 3.10
Classifier: Programming Language :: Python :: 3.11
Classifier: Programming Language :: Python :: 3.12
Classifier: Programming Language :: Python :: 3.13
Classifier: Programming Language :: Python :: 3.14
Classifier: Topic :: Scientific/Engineering :: Mathematics
Classifier: Topic :: Software Development :: Libraries :: Python Modules
Requires-Python: >=3.9
License-File: LICENSE
Requires-Dist: numpy
Requires-Dist: scipy
Provides-Extra: dev
Requires-Dist: pytest>=7.0; extra == "dev"
Requires-Dist: pytest-cov; extra == "dev"
Requires-Dist: black; extra == "dev"
Requires-Dist: isort; extra == "dev"
Requires-Dist: flake8; extra == "dev"
Dynamic: license-file
